mtppy/__init__.py
mtppy/active_elements.py
mtppy/attribute.py
mtppy/command_codes.py
mtppy/command_en_control.py
mtppy/communication_object.py
mtppy/indicator_elements.py
mtppy/mtp_generator.py
mtppy/opcua_server_pea.py
mtppy/operation_elements.py
mtppy/operation_source_mode.py
mtppy/procedure.py
mtppy/procedure_control.py
mtppy/service.py
mtppy/state_codes.py
mtppy/state_machine.py
mtppy/suc_data_assembly.py
mtppy/thread_control.py
MTPPy-1.1.1.dist-info/LICENSE.md
MTPPy-1.1.1.dist-info/METADATA
MTPPy-1.1.1.dist-info/WHEEL
MTPPy-1.1.1.dist-info/top_level.txt
MTPPy-1.1.1.dist-info/RECORD
