Metadata-Version: 2.1
Name: MTPPy
Version: 1.1.1
Summary: Open-source modular automation
Home-page: UNKNOWN
Author: Valentin Khaydarov, Tobias Kock
Author-email: valentin.khaydarov@gmail.com
License: UNKNOWN
Platform: UNKNOWN
License-File: LICENSE.md
